Compiled from "Annotations.java"
class classes.test.Annotations extends java.lang.Object
  SourceFile: "Annotations.java"
  Deprecated: length = 0x
   
  RuntimeVisibleAnnotations: length = 0x6
   00 01 00 13 00 00 
  minor version: 0
  major version: 50
  Constant pool:
const #1 = Method	#6.#20;	//  java/lang/Object."<init>":()V
const #2 = class	#21;	//  classes/test/Annotations
const #3 = Method	#22.#23;	//  java/lang/Class.getAnnotations:()[Ljava/lang/annotation/Annotation;
const #4 = Field	#24.#25;	//  java/lang/System.out:Ljava/io/PrintStream;
const #5 = Method	#26.#27;	//  java/io/PrintStream.println:(Ljava/lang/Object;)V
const #6 = class	#28;	//  java/lang/Object
const #7 = Asciz	<init>;
const #8 = Asciz	()V;
const #9 = Asciz	Code;
const #10 = Asciz	LineNumberTable;
const #11 = Asciz	main;
const #12 = Asciz	([Ljava/lang/String;)V;
const #13 = Asciz	StackMapTable;
const #14 = class	#29;	//  "[Ljava/lang/annotation/Annotation;"
const #15 = Asciz	SourceFile;
const #16 = Asciz	Annotations.java;
const #17 = Asciz	Deprecated;
const #18 = Asciz	RuntimeVisibleAnnotations;
const #19 = Asciz	Ljava/lang/Deprecated;;
const #20 = NameAndType	#7:#8;//  "<init>":()V
const #21 = Asciz	classes/test/Annotations;
const #22 = class	#30;	//  java/lang/Class
const #23 = NameAndType	#31:#32;//  getAnnotations:()[Ljava/lang/annotation/Annotation;
const #24 = class	#33;	//  java/lang/System
const #25 = NameAndType	#34:#35;//  out:Ljava/io/PrintStream;
const #26 = class	#36;	//  java/io/PrintStream
const #27 = NameAndType	#37:#38;//  println:(Ljava/lang/Object;)V
const #28 = Asciz	java/lang/Object;
const #29 = Asciz	[Ljava/lang/annotation/Annotation;;
const #30 = Asciz	java/lang/Class;
const #31 = Asciz	getAnnotations;
const #32 = Asciz	()[Ljava/lang/annotation/Annotation;;
const #33 = Asciz	java/lang/System;
const #34 = Asciz	out;
const #35 = Asciz	Ljava/io/PrintStream;;
const #36 = Asciz	java/io/PrintStream;
const #37 = Asciz	println;
const #38 = Asciz	(Ljava/lang/Object;)V;

{
classes.test.Annotations();
  Code:
   Stack=1, Locals=1, Args_size=1
   0:	aload_0
   1:	invokespecial	#1; //Method java/lang/Object."<init>":()V
   4:	return
  LineNumberTable: 
   line 6: 0


public static void main(java.lang.String[]);
  Code:
   Stack=2, Locals=5, Args_size=1
   0:	ldc_w	#2; //class classes/test/Annotations
   3:	invokevirtual	#3; //Method java/lang/Class.getAnnotations:()[Ljava/lang/annotation/Annotation;
   6:	astore_1
   7:	aload_1
   8:	arraylength
   9:	istore_2
   10:	iconst_0
   11:	istore_3
   12:	iload_3
   13:	iload_2
   14:	if_icmpge	36
   17:	aload_1
   18:	iload_3
   19:	aaload
   20:	astore	4
   22:	getstatic	#4; //Field java/lang/System.out:Ljava/io/PrintStream;
   25:	aload	4
   27:	invokevirtual	#5; //Method java/io/PrintStream.println:(Ljava/lang/Object;)V
   30:	iinc	3, 1
   33:	goto	12
   36:	return
  LineNumberTable: 
   line 8: 0
   line 9: 22
   line 8: 30
   line 11: 36

  StackMapTable: number_of_entries = 2
   frame_type = 254 /* append */
     offset_delta = 12
     locals = [ class "[Ljava/lang/annotation/Annotation;", int, int ]
   frame_type = 248 /* chop */
     offset_delta = 23


}

