Compiled from "Threading.java"
public class classes.test.Threading extends java.lang.Thread
  SourceFile: "Threading.java"
  minor version: 0
  major version: 50
  Constant pool:
const #1 = Method	#31.#49;	//  java/lang/Thread."<init>":(Ljava/lang/String;)V
const #2 = Field	#50.#51;	//  java/lang/System.out:Ljava/io/PrintStream;
const #3 = class	#52;	//  java/lang/StringBuilder
const #4 = Method	#3.#53;	//  java/lang/StringBuilder."<init>":()V
const #5 = String	#54;	//  hello from 
const #6 = Method	#3.#55;	//  java/lang/StringBuilder.append:(Ljava/lang/String;)Ljava/lang/StringBuilder;
const #7 = Method	#31.#56;	//  java/lang/Thread.currentThread:()Ljava/lang/Thread;
const #8 = Method	#31.#57;	//  java/lang/Thread.getName:()Ljava/lang/String;
const #9 = Method	#3.#58;	//  java/lang/StringBuilder.toString:()Ljava/lang/String;
const #10 = Method	#59.#60;	//  java/io/PrintStream.println:(Ljava/lang/String;)V
const #11 = Method	#31.#61;	//  java/lang/Thread.interrupt:()V
const #12 = String	#62;	//  main thread was interrupted: 
const #13 = Method	#31.#63;	//  java/lang/Thread.interrupted:()Z
const #14 = Method	#3.#64;	//  java/lang/StringBuilder.append:(Z)Ljava/lang/StringBuilder;
const #15 = class	#65;	//  classes/test/Threading
const #16 = String	#66;	//  hello-thread
const #17 = Method	#15.#49;	//  classes/test/Threading."<init>":(Ljava/lang/String;)V
const #18 = Method	#15.#67;	//  classes/test/Threading.holdsLock:(Ljava/lang/Object;)Z
const #19 = Method	#59.#68;	//  java/io/PrintStream.println:(Z)V
const #20 = Method	#15.#69;	//  classes/test/Threading.isInterrupted:()Z
const #21 = Method	#15.#70;	//  classes/test/Threading.run:()V
const #22 = Method	#15.#71;	//  classes/test/Threading.start:()V
const #23 = Method	#15.#72;	//  classes/test/Threading.join:()V
const #24 = String	#73;	//  joined in 
const #25 = class	#74;	//  classes/test/Q
const #26 = Method	#25.#53;	//  classes/test/Q."<init>":()V
const #27 = class	#75;	//  classes/test/Producer
const #28 = Method	#27.#76;	//  classes/test/Producer."<init>":(Lclasses/test/Q;)V
const #29 = class	#77;	//  classes/test/Consumer
const #30 = Method	#29.#76;	//  classes/test/Consumer."<init>":(Lclasses/test/Q;)V
const #31 = class	#78;	//  java/lang/Thread
const #32 = Asciz	<init>;
const #33 = Asciz	(Ljava/lang/String;)V;
const #34 = Asciz	Code;
const #35 = Asciz	LineNumberTable;
const #36 = Asciz	run;
const #37 = Asciz	()V;
const #38 = Asciz	main;
const #39 = Asciz	([Ljava/lang/String;)V;
const #40 = Asciz	StackMapTable;
const #41 = class	#79;	//  "[Ljava/lang/String;"
const #42 = class	#65;	//  classes/test/Threading
const #43 = class	#80;	//  java/lang/Object
const #44 = class	#81;	//  java/lang/Throwable
const #45 = Asciz	Exceptions;
const #46 = class	#82;	//  java/lang/InterruptedException
const #47 = Asciz	SourceFile;
const #48 = Asciz	Threading.java;
const #49 = NameAndType	#32:#33;//  "<init>":(Ljava/lang/String;)V
const #50 = class	#83;	//  java/lang/System
const #51 = NameAndType	#84:#85;//  out:Ljava/io/PrintStream;
const #52 = Asciz	java/lang/StringBuilder;
const #53 = NameAndType	#32:#37;//  "<init>":()V
const #54 = Asciz	hello from ;
const #55 = NameAndType	#86:#87;//  append:(Ljava/lang/String;)Ljava/lang/StringBuilder;
const #56 = NameAndType	#88:#89;//  currentThread:()Ljava/lang/Thread;
const #57 = NameAndType	#90:#91;//  getName:()Ljava/lang/String;
const #58 = NameAndType	#92:#91;//  toString:()Ljava/lang/String;
const #59 = class	#93;	//  java/io/PrintStream
const #60 = NameAndType	#94:#33;//  println:(Ljava/lang/String;)V
const #61 = NameAndType	#95:#37;//  interrupt:()V
const #62 = Asciz	main thread was interrupted: ;
const #63 = NameAndType	#96:#97;//  interrupted:()Z
const #64 = NameAndType	#86:#98;//  append:(Z)Ljava/lang/StringBuilder;
const #65 = Asciz	classes/test/Threading;
const #66 = Asciz	hello-thread;
const #67 = NameAndType	#99:#100;//  holdsLock:(Ljava/lang/Object;)Z
const #68 = NameAndType	#94:#101;//  println:(Z)V
const #69 = NameAndType	#102:#97;//  isInterrupted:()Z
const #70 = NameAndType	#36:#37;//  run:()V
const #71 = NameAndType	#103:#37;//  start:()V
const #72 = NameAndType	#104:#37;//  join:()V
const #73 = Asciz	joined in ;
const #74 = Asciz	classes/test/Q;
const #75 = Asciz	classes/test/Producer;
const #76 = NameAndType	#32:#105;//  "<init>":(Lclasses/test/Q;)V
const #77 = Asciz	classes/test/Consumer;
const #78 = Asciz	java/lang/Thread;
const #79 = Asciz	[Ljava/lang/String;;
const #80 = Asciz	java/lang/Object;
const #81 = Asciz	java/lang/Throwable;
const #82 = Asciz	java/lang/InterruptedException;
const #83 = Asciz	java/lang/System;
const #84 = Asciz	out;
const #85 = Asciz	Ljava/io/PrintStream;;
const #86 = Asciz	append;
const #87 = Asciz	(Ljava/lang/String;)Ljava/lang/StringBuilder;;
const #88 = Asciz	currentThread;
const #89 = Asciz	()Ljava/lang/Thread;;
const #90 = Asciz	getName;
const #91 = Asciz	()Ljava/lang/String;;
const #92 = Asciz	toString;
const #93 = Asciz	java/io/PrintStream;
const #94 = Asciz	println;
const #95 = Asciz	interrupt;
const #96 = Asciz	interrupted;
const #97 = Asciz	()Z;
const #98 = Asciz	(Z)Ljava/lang/StringBuilder;;
const #99 = Asciz	holdsLock;
const #100 = Asciz	(Ljava/lang/Object;)Z;
const #101 = Asciz	(Z)V;
const #102 = Asciz	isInterrupted;
const #103 = Asciz	start;
const #104 = Asciz	join;
const #105 = Asciz	(Lclasses/test/Q;)V;

{
public classes.test.Threading(java.lang.String);
  Code:
   Stack=2, Locals=2, Args_size=2
   0:	aload_0
   1:	aload_1
   2:	invokespecial	#1; //Method java/lang/Thread."<init>":(Ljava/lang/String;)V
   5:	return
  LineNumberTable: 
   line 6: 0
   line 7: 5


public void run();
  Code:
   Stack=3, Locals=1, Args_size=1
   0:	getstatic	#2; //Field java/lang/System.out:Ljava/io/PrintStream;
   3:	new	#3; //class java/lang/StringBuilder
   6:	dup
   7:	invokespecial	#4; //Method java/lang/StringBuilder."<init>":()V
   10:	ldc	#5; //String hello from 
   12:	invokevirtual	#6; //Method java/lang/StringBuilder.append:(Ljava/lang/String;)Ljava/lang/StringBuilder;
   15:	invokestatic	#7; //Method java/lang/Thread.currentThread:()Ljava/lang/Thread;
   18:	invokevirtual	#8; //Method java/lang/Thread.getName:()Ljava/lang/String;
   21:	invokevirtual	#6; //Method java/lang/StringBuilder.append:(Ljava/lang/String;)Ljava/lang/StringBuilder;
   24:	invokevirtual	#9; //Method java/lang/StringBuilder.toString:()Ljava/lang/String;
   27:	invokevirtual	#10; //Method java/io/PrintStream.println:(Ljava/lang/String;)V
   30:	return
  LineNumberTable: 
   line 9: 0
   line 10: 30


public static void main(java.lang.String[])   throws java.lang.InterruptedException;
  Code:
   Stack=3, Locals=4, Args_size=1
   0:	invokestatic	#7; //Method java/lang/Thread.currentThread:()Ljava/lang/Thread;
   3:	invokevirtual	#11; //Method java/lang/Thread.interrupt:()V
   6:	getstatic	#2; //Field java/lang/System.out:Ljava/io/PrintStream;
   9:	new	#3; //class java/lang/StringBuilder
   12:	dup
   13:	invokespecial	#4; //Method java/lang/StringBuilder."<init>":()V
   16:	ldc	#12; //String main thread was interrupted: 
   18:	invokevirtual	#6; //Method java/lang/StringBuilder.append:(Ljava/lang/String;)Ljava/lang/StringBuilder;
   21:	invokestatic	#7; //Method java/lang/Thread.currentThread:()Ljava/lang/Thread;
   24:	pop
   25:	invokestatic	#13; //Method java/lang/Thread.interrupted:()Z
   28:	invokevirtual	#14; //Method java/lang/StringBuilder.append:(Z)Ljava/lang/StringBuilder;
   31:	invokevirtual	#9; //Method java/lang/StringBuilder.toString:()Ljava/lang/String;
   34:	invokevirtual	#10; //Method java/io/PrintStream.println:(Ljava/lang/String;)V
   37:	new	#15; //class classes/test/Threading
   40:	dup
   41:	ldc	#16; //String hello-thread
   43:	invokespecial	#17; //Method "<init>":(Ljava/lang/String;)V
   46:	astore_1
   47:	getstatic	#2; //Field java/lang/System.out:Ljava/io/PrintStream;
   50:	aload_1
   51:	pop
   52:	aload_1
   53:	invokestatic	#18; //Method holdsLock:(Ljava/lang/Object;)Z
   56:	invokevirtual	#19; //Method java/io/PrintStream.println:(Z)V
   59:	aload_1
   60:	dup
   61:	astore_2
   62:	monitorenter
   63:	getstatic	#2; //Field java/lang/System.out:Ljava/io/PrintStream;
   66:	aload_1
   67:	pop
   68:	aload_1
   69:	invokestatic	#18; //Method holdsLock:(Ljava/lang/Object;)Z
   72:	invokevirtual	#19; //Method java/io/PrintStream.println:(Z)V
   75:	aload_2
   76:	monitorexit
   77:	goto	85
   80:	astore_3
   81:	aload_2
   82:	monitorexit
   83:	aload_3
   84:	athrow
   85:	getstatic	#2; //Field java/lang/System.out:Ljava/io/PrintStream;
   88:	aload_1
   89:	invokevirtual	#20; //Method isInterrupted:()Z
   92:	invokevirtual	#19; //Method java/io/PrintStream.println:(Z)V
   95:	aload_1
   96:	invokevirtual	#21; //Method run:()V
   99:	aload_1
   100:	invokevirtual	#22; //Method start:()V
   103:	aload_1
   104:	invokevirtual	#23; //Method join:()V
   107:	getstatic	#2; //Field java/lang/System.out:Ljava/io/PrintStream;
   110:	new	#3; //class java/lang/StringBuilder
   113:	dup
   114:	invokespecial	#4; //Method java/lang/StringBuilder."<init>":()V
   117:	ldc	#24; //String joined in 
   119:	invokevirtual	#6; //Method java/lang/StringBuilder.append:(Ljava/lang/String;)Ljava/lang/StringBuilder;
   122:	invokestatic	#7; //Method java/lang/Thread.currentThread:()Ljava/lang/Thread;
   125:	invokevirtual	#8; //Method java/lang/Thread.getName:()Ljava/lang/String;
   128:	invokevirtual	#6; //Method java/lang/StringBuilder.append:(Ljava/lang/String;)Ljava/lang/StringBuilder;
   131:	invokevirtual	#9; //Method java/lang/StringBuilder.toString:()Ljava/lang/String;
   134:	invokevirtual	#10; //Method java/io/PrintStream.println:(Ljava/lang/String;)V
   137:	new	#25; //class classes/test/Q
   140:	dup
   141:	invokespecial	#26; //Method classes/test/Q."<init>":()V
   144:	astore_2
   145:	new	#27; //class classes/test/Producer
   148:	dup
   149:	aload_2
   150:	invokespecial	#28; //Method classes/test/Producer."<init>":(Lclasses/test/Q;)V
   153:	pop
   154:	new	#29; //class classes/test/Consumer
   157:	dup
   158:	aload_2
   159:	invokespecial	#30; //Method classes/test/Consumer."<init>":(Lclasses/test/Q;)V
   162:	pop
   163:	return
  Exception table:
   from   to  target type
    63    77    80   any
    80    83    80   any
  LineNumberTable: 
   line 12: 0
   line 13: 6
   line 15: 37
   line 16: 47
   line 17: 59
   line 18: 63
   line 19: 75
   line 20: 85
   line 21: 95
   line 22: 99
   line 23: 103
   line 24: 107
   line 25: 137
   line 26: 145
   line 27: 154
   line 28: 163

  StackMapTable: number_of_entries = 2
   frame_type = 255 /* full_frame */
     offset_delta = 80
     locals = [ class "[Ljava/lang/String;", class classes/test/Threading, class java/lang/Object ]
     stack = [ class java/lang/Throwable ]
   frame_type = 250 /* chop */
     offset_delta = 4

  Exceptions: 
   throws java.lang.InterruptedException
}

